README.md
setup.py
Wuhan2019nCoV.egg-info/PKG-INFO
Wuhan2019nCoV.egg-info/SOURCES.txt
Wuhan2019nCoV.egg-info/dependency_links.txt
Wuhan2019nCoV.egg-info/entry_points.txt
Wuhan2019nCoV.egg-info/requires.txt
Wuhan2019nCoV.egg-info/top_level.txt
wuhanncov/__init__.py
wuhanncov/check_loop.py
wuhanncov/dingxiangyuan.py
wuhanncov/fenghuang.py
wuhanncov/lark.py
wuhanncov/osx.py
wuhanncov/output_helper.py
wuhanncov/terminalcolor.py
wuhanncov/toutiao.py
wuhanncov/wangyi.py
wuhanncov/yanshixinwen.py