Metadata-Version: 1.1
Name: Wuhan2019nCoV
Version: 0.1.4
Summary: This tool is used for crawl Wuhan 2019nCov Info
Home-page: https://github.com/jacksgong/wuhan-2019ncov
Author: Jacksgong
Author-email: igzhenjie@gmail.com
License: Apache2
Keywords: crawler,wuhan,2019nCov
Platform: UNKNOWN
Classifier: Development Status :: 5 - Production/Stable
Classifier: License :: OSI Approved :: Apache Software License
Classifier: Programming Language :: Python :: 2.7
Classifier: Programming Language :: Python :: 3
Classifier: Programming Language :: Python :: 3.3
Classifier: Programming Language :: Python :: 3.4
Classifier: Programming Language :: Python :: 3.5
Classifier: Programming Language :: Python :: 3.6
